pd/__init__.py
pd/pdd.py
tests/__init__.py
tests/test_pd.py
pd-0.0.4.dist-info/LICENSE
pd-0.0.4.dist-info/METADATA
pd-0.0.4.dist-info/WHEEL
pd-0.0.4.dist-info/top_level.txt
pd-0.0.4.dist-info/RECORD
