Metadata-Version: 2.1
Name: pd
Version: 0.0.4
Summary: more detailed python backtraces (similar to backtrace module)
Home-page: https://github.com/MoserMichael/visual-python-strace
Author: Michael Moser
Author-email: moser.michael@gmail.com
License: BSD
Keywords: backtrace,debugging
Platform: UNKNOWN
Classifier: Topic :: Utilities
Classifier: Intended Audience :: Developers
Classifier: Operating System :: OS Independent
Classifier: License :: OSI Approved :: BSD License
